{"generated_at":"2026-07-24T01:05:25+00:00","window_days":7,"poll_minutes":63,"note":"Observed close-out = last-seen minus first-seen plus one poll interval; true duration is within \u00b163 min. 'Momentary' = seen in a single poll (resolved in under ~one interval) \u2014 the public-data cousin of a MAIFI momentary-interruption metric. True brownout/voltage-sag data is utility-internal and only surfaces in PUCO reliability filings.","regions":{"BGE":{"resolved":103,"avg_min":2632.7,"median_min":1188.9,"momentary":7,"momentary_pct":6.8},"DC-PEPCO":{"resolved":25,"avg_min":771.4,"median_min":92.2,"momentary":10,"momentary_pct":40.0},"DE-DELMARVA":{"resolved":67,"avg_min":1642.4,"median_min":391.6,"momentary":21,"momentary_pct":31.3},"GA-GPC":{"resolved":49,"avg_min":1490.8,"median_min":1542.2,"momentary":7,"momentary_pct":14.3},"IN-DUKE":{"resolved":495,"avg_min":129.3,"median_min":63.0,"momentary":267,"momentary_pct":53.9},"IN-IM":{"resolved":4,"avg_min":746.4,"median_min":63.0,"momentary":3,"momentary_pct":75.0},"KY-AEP":{"resolved":2,"avg_min":893.9,"median_min":893.9,"momentary":0,"momentary_pct":0.0},"MA-NGRID":{"resolved":15,"avg_min":2272.6,"median_min":123.4,"momentary":7,"momentary_pct":46.7},"MD-WV":{"resolved":7,"avg_min":2400.0,"median_min":63.0,"momentary":2,"momentary_pct":28.6},"NC-DEC":{"resolved":3038,"avg_min":170.4,"median_min":106.5,"momentary":1441,"momentary_pct":47.4},"NC-DEP":{"resolved":2908,"avg_min":148.0,"median_min":63.0,"momentary":1458,"momentary_pct":50.1},"NE-EVERSOURCE":{"resolved":160,"avg_min":2923.0,"median_min":423.9,"momentary":10,"momentary_pct":6.2},"NJ":{"resolved":4,"avg_min":2062.4,"median_min":2083.6,"momentary":1,"momentary_pct":25.0},"NJ-ACE":{"resolved":67,"avg_min":1823.7,"median_min":652.4,"momentary":22,"momentary_pct":32.8},"NJ-PSEG":{"resolved":56,"avg_min":2004.1,"median_min":63.0,"momentary":31,"momentary_pct":55.4},"NY-CENHUD":{"resolved":27,"avg_min":2748.9,"median_min":1769.5,"momentary":9,"momentary_pct":33.3},"NY-NGRID":{"resolved":29,"avg_min":2844.5,"median_min":389.4,"momentary":9,"momentary_pct":31.0},"OH":{"resolved":18,"avg_min":3141.0,"median_min":4205.4,"momentary":1,"momentary_pct":5.6},"OH-AES":{"resolved":458,"avg_min":176.2,"median_min":63.0,"momentary":231,"momentary_pct":50.4},"OH-DUKE":{"resolved":914,"avg_min":226.1,"median_min":129.1,"momentary":381,"momentary_pct":41.7},"PA-NY":{"resolved":39,"avg_min":1833.0,"median_min":494.0,"momentary":3,"momentary_pct":7.7},"PA-PPL":{"resolved":895,"avg_min":221.9,"median_min":112.2,"momentary":388,"momentary_pct":43.4},"PECO":{"resolved":54,"avg_min":4094.3,"median_min":3994.2,"momentary":10,"momentary_pct":18.5},"SC-DOM":{"resolved":13,"avg_min":784.4,"median_min":87.7,"momentary":5,"momentary_pct":38.5},"VA-DOM":{"resolved":110,"avg_min":3057.4,"median_min":2872.3,"momentary":23,"momentary_pct":20.9},"VA-NOVEC":{"resolved":62,"avg_min":117.6,"median_min":63.0,"momentary":34,"momentary_pct":54.8},"VAWV-APCO":{"resolved":35,"avg_min":4309.5,"median_min":5480.2,"momentary":5,"momentary_pct":14.3}},"longest":[{"region":"PECO","minutes":8611,"customers":1157},{"region":"VA-DOM","minutes":8551,"customers":2363},{"region":"PECO","minutes":8408,"customers":1160},{"region":"NY-CENHUD","minutes":8363,"customers":207},{"region":"PECO","minutes":8262,"customers":110}]}